{
    "error": 0,
    "data": [
             {
             "room_id": "584854",
             "room_src": "https://rpic.douyucdn.cn/live-cover/appCovers/2019/01/17/584854_20190117162459_small.jpg",
             "vertical_src": "https://rpic.douyucdn.cn/live-cover/appCovers/2019/01/17/584854_20190117162459_big.jpg",
             "isVertical": 1,
             "cate_id": 201,
             "room_name": "周星冲鸭，冲呀。",
             "show_status": "1",
             "subject": "",
             "show_time": "1548748641",
             "owner_uid": "43239450",
             "specific_catalog": "",
             "specific_status": "0",
             "vod_quality": "0",
             "nickname": "Abby林玲",
             "hn": 0,
             "online": 70398,
             "game_name": "颜值",
             "child_id": 581,
             "avatar_mid": "https://apic.douyucdn.cn/upload/avatar_v3/201901/4bc318a2cbbe43ef86ff84b866f8de8c_middle.jpg",
             "avatar_small": "https://apic.douyucdn.cn/upload/avatar_v3/201901/4bc318a2cbbe43ef86ff84b866f8de8c_small.jpg",
             "jumpUrl": "",
             "nrt": 0,
             "ranktype": 0,
             "rmf1": 0,
             "rmf2": 0,
             "rmf3": 1,
             "rmf4": 0,
             "rmf5": 0,
             "show_type": 0,
             "is_noble_rec": 0,
             "anchor_city": "福州市"
             },
             {
             "room_id": "5948059",
             "room_src": "https://rpic.douyucdn.cn/live-cover/appCovers/2019/01/22/5948059_20190122095006_small.jpg",
             "vertical_src": "https://rpic.douyucdn.cn/live-cover/appCovers/2019/01/22/5948059_20190122095006_big.jpg",
             "isVertical": 1,
             "cate_id": 201,
             "room_name": "还要多久才能和你接近",
             "show_status": "1",
             "subject": "",
             "show_time": "1548746249",
             "owner_uid": "241841643",
             "specific_catalog": "",
             "specific_status": "0",
             "vod_quality": "0",
             "nickname": "一只傻茹呀",
             "hn": 0,
             "online": 75232,
             "game_name": "颜值",
             "child_id": 581,
             "avatar_mid": "https://apic.douyucdn.cn/upload/avatar_v3/201901/6f47ff9af0c34506a4bfbe90ba8dc61d_middle.jpg",
             "avatar_small": "https://apic.douyucdn.cn/upload/avatar_v3/201901/6f47ff9af0c34506a4bfbe90ba8dc61d_small.jpg",
             "jumpUrl": "",
             "nrt": 0,
             "ranktype": 0,
             "rmf1": 0,
             "rmf2": 0,
             "rmf3": 0,
             "rmf4": 0,
             "rmf5": 0,
             "show_type": 0,
             "is_noble_rec": 0,
             "anchor_city": "长沙市"
             },
             {
             "room_id": "6281453",
             "room_src": "https://rpic.douyucdn.cn/live-cover/appCovers/2019/01/21/6281453_20190121215045_small.jpg",
             "vertical_src": "https://rpic.douyucdn.cn/live-cover/appCovers/2019/01/21/6281453_20190121215045_big.jpg",
             "isVertical": 1,
             "cate_id": 201,
             "room_name": "奔向16级的小樊",
             "show_status": "1",
             "subject": "",
             "show_time": "1548749805",
             "owner_uid": "255374629",
             "specific_catalog": "",
             "specific_status": "0",
             "vod_quality": "0",
             "nickname": "葛小樊",
             "hn": 0,
             "online": 2657,
             "game_name": "颜值",
             "child_id": 581,
             "avatar_mid": "https://apic.douyucdn.cn/upload/avatar_v3/201901/87c704d0e2634594bd8791f1e85693b5_middle.jpg",
             "avatar_small": "https://apic.douyucdn.cn/upload/avatar_v3/201901/87c704d0e2634594bd8791f1e85693b5_small.jpg",
             "jumpUrl": "",
             "nrt": 0,
             "ranktype": 0,
             "rmf1": 0,
             "rmf2": 0,
             "rmf3": 0,
             "rmf4": 0,
             "rmf5": 0,
             "show_type": 0,
             "is_noble_rec": 0,
             "anchor_city": "北京市"
             },
             {
             "room_id": "3866447",
             "room_src": "https://rpic.douyucdn.cn/live-cover/appCovers/2018/04/12/3866447_20180412205544_small.jpg",
             "vertical_src": "https://rpic.douyucdn.cn/live-cover/appCovers/2018/04/12/3866447_20180412205544_big.jpg",
             "isVertical": 1,
             "cate_id": 201,
             "room_name": "十二月老铁能说会唠",
             "show_status": "1",
             "subject": "",
             "show_time": "1548749115",
             "owner_uid": "1269694",
             "specific_catalog": "",
             "specific_status": "0",
             "vod_quality": "0",
             "nickname": "十二月老铁",
             "hn": 0,
             "online": 628665,
             "game_name": "颜值",
             "child_id": 581,
             "avatar_mid": "https://apic.douyucdn.cn/upload/avanew/face/201802/13/02/f3526fc3a867efad86fbb4d9279387e7_middle.jpg",
             "avatar_small": "https://apic.douyucdn.cn/upload/avanew/face/201802/13/02/f3526fc3a867efad86fbb4d9279387e7_small.jpg",
             "jumpUrl": "",
             "nrt": 0,
             "ranktype": 0,
             "rmf1": 0,
             "rmf2": 0,
             "rmf3": 0,
             "rmf4": 0,
             "rmf5": 0,
             "show_type": 0,
             "is_noble_rec": 0,
             "anchor_city": "沈阳市"
             }
             ]
}
